vim_quest_cli/__init__.py
vim_quest_cli/__main__.py
vim_quest_cli/corpus/__init__.py
vim_quest_cli/corpus/labyrinth.py
vim_quest_cli/corpus.py
vim_quest_cli/deps/EnumAction.py
vim_quest_cli/deps/__init__.py
vim_quest_cli/deps/ansi/__init__.py
vim_quest_cli/deps/ansi/color.py
vim_quest_cli/deps/ansi/colour/__init__.py
vim_quest_cli/deps/ansi/colour/base.py
vim_quest_cli/deps/ansi/colour/bg.py
vim_quest_cli/deps/ansi/colour/fg.py
vim_quest_cli/deps/ansi/colour/fx.py
vim_quest_cli/deps/ansi/colour/rgb.py
vim_quest_cli/deps/ansi/cursor.py
vim_quest_cli/deps/ansi/iterm.py
vim_quest_cli/deps/ansi/osc.py
vim_quest_cli/deps/ansi/py.typed
vim_quest_cli/deps/ansi/sequence.py
vim_quest_cli/deps/create_modules_if_is_js.py
vim_quest_cli/deps/is_js.py
vim_quest_cli/deps/project2singleFile_export.py
vim_quest_cli/deps/prompt_toolkit/__init__.py
vim_quest_cli/deps/prompt_toolkit/ansi_escape_sequences.py
vim_quest_cli/deps/prompt_toolkit/keys.py
vim_quest_cli/deps/stdin_reader.py
vim_quest_cli/deps/test_stdin.py
vim_quest_cli/engine/__init__.py
vim_quest_cli/engine/command.py
vim_quest_cli/engine/engine_interface.py
vim_quest_cli/engine/pure_python/KeyPressBindingHelper.py
vim_quest_cli/engine/pure_python/__init__.py
vim_quest_cli/engine/pure_python/bindings.py
vim_quest_cli/engine/pure_python/engine_helper.py
vim_quest_cli/engine/pure_python/pure_python_engine.py
vim_quest_cli/engine/vim_exe/__init__.py
vim_quest_cli/engine/vim_exe/resources/__init__.py
vim_quest_cli/engine/vim_exe/resources/save_state.vim
vim_quest_cli/engine/vim_exe/vim_exe_engine.py
vim_quest_cli/interface/__init__.py
vim_quest_cli/interface/curses_window.py
vim_quest_cli/interface/mapping.py
vim_quest_cli/interface/terminal_ui.py
vim_quest_cli/mode/__init__.py
vim_quest_cli/mode/enemies_coming_at_you.py
vim_quest_cli/mode/go_to_x.py
vim_quest_cli/mode/labyrinth.py
vim_quest_cli/mode/mode_container.py
vim_quest_cli/mode/mode_interface.py
vim_quest_cli/mode/search_x_and_destroy.py
vim_quest_cli/mode/welcome.py
vim_quest_cli-0.1.15.dist-info/entry_points.txt
vim_quest_cli-0.1.15.dist-info/WHEEL
vim_quest_cli-0.1.15.dist-info/METADATA
vim_quest_cli-0.1.15.dist-info/RECORD
