Metadata-Version: 2.1
Name: vim-quest-cli
Version: 0.1.15
Summary: 
Author: Stolati
Author-email: stolati@gmail.com
Requires-Python: >=3.8,<4.0
Classifier: Programming Language :: Python :: 3
Classifier: Programming Language :: Python :: 3.8
Classifier: Programming Language :: Python :: 3.9
Classifier: Programming Language :: Python :: 3.10
Classifier: Programming Language :: Python :: 3.11
Requires-Dist: ansi (>=0.3.6,<0.4.0)
Requires-Dist: argparse-dataclass (>=0.2.1,<0.3.0)
